{
	"info": {
		"_postman_id": "1418fb87-9ad5-4d12-98d7-a68a82e3d82d",
		"name": "Products Collection",
		"schema": "https://schema.getpostman.com/json/collection/v2.1.0/collection.json",
		"_exporter_id": "35947998"
	},
	"item": [
		{
			"name": "Adding product",
			"request": {
				"method": "POST",
				"header": [],
				"body": {
					"mode": "raw",
					"raw": "{\r\n    \"name\": \"shampoo\",\r\n    \"description\": \"product for hair care and cleaning\",\r\n    \"price\":4.75\r\n}",
					"options": {
						"raw": {
							"language": "json"
						}
					}
				},
				"url": {
					"raw": "localhost:8080/products",
					"host": [
						"localhost"
					],
					"port": "8080",
					"path": [
						"products"
					]
				}
			},
			"response": []
		},
		{
			"name": "Update product",
			"request": {
				"method": "PUT",
				"header": [],
				"body": {
					"mode": "raw",
					"raw": "{\r\n    \"name\":\"notebook\",\r\n    \"description\":\"17*25cm notebook\",\r\n    \"price\":0.5\r\n}",
					"options": {
						"raw": {
							"language": "json"
						}
					}
				},
				"url": {
					"raw": "localhost:8080/products/2",
					"host": [
						"localhost"
					],
					"port": "8080",
					"path": [
						"products",
						"2"
					]
				}
			},
			"response": []
		},
		{
			"name": "Delete product",
			"request": {
				"method": "DELETE",
				"header": [],
				"url": {
					"raw": "localhost:8080/products/1",
					"host": [
						"localhost"
					],
					"port": "8080",
					"path": [
						"products",
						"1"
					]
				}
			},
			"response": []
		},
		{
			"name": "Getting by ID",
			"request": {
				"method": "GET",
				"header": [],
				"url": {
					"raw": "localhost:8080/products/2",
					"host": [
						"localhost"
					],
					"port": "8080",
					"path": [
						"products",
						"2"
					]
				}
			},
			"response": []
		},
		{
			"name": "Getting all products",
			"request": {
				"method": "GET",
				"header": [],
				"url": {
					"raw": "localhost:8080/products",
					"host": [
						"localhost"
					],
					"port": "8080",
					"path": [
						"products"
					]
				}
			},
			"response": []
		}
	]
}